{
    "name": "unifi-controller",
    "longname": "Unifi Controller",
    "description": "Interact with a Unifi Controller",
    "capabilities": [],
    "notes": "",
    "version": "1.0.1",
    "icon": "mdiWifi",
    "author": "Ryan McCartney",
    "license": "Apache-2.0",
    "status": "stable",
    "needsContainer": true,
    "devmounts": ["api", "services", "workers"],
    "protectedRoutes": ["config"],
    "defaultconfig": {
        "id": "",
        "order": 0,
        "needsConfigured": true,
        "title": "",
        "module": "unifi-controller",
        "description": "",
        "notes": "",
        "enabled": false,
        "address": "",
        "username": "",
        "password": "",
        "port": 8443,
        "sites": []
    }
}
